[
  {
    "id": 1,
    "name": "John Doe",
    "picture": "https://res.cloudinary.com/dja4hd07v/image/upload/v1776313666/images_3_sfvumm.jpg",
    "email": "john@example.com",
    "days_since_contact": 12,
    "status": "overdue",
    "tags": ["college", "close friend"],
    "bio": "Met in university. Love hiking together.",
    "goal": 14,
    "next_due_date": "2025-07-20"
  },
  {
    "id": 2,
    "name": "Sarah Khan",
    "picture": "https://res.cloudinary.com/dja4hd07v/image/upload/f_auto,q_auto/images_2_ihoql6",
    "email": "sarah@example.com",
    "days_since_contact": 3,
    "status": "active",
    "tags": ["work", "design"],
    "bio": "Colleague from design team.",
    "goal": 7,
    "next_due_date": "2025-07-10"
  },
  {
    "id": 3,
    "name": "Michael Lee",
    "picture": "https://res.cloudinary.com/dja4hd07v/image/upload/v1776313666/images_5_tv0uzw.jpg",
    "email": "michael@example.com",
    "days_since_contact": 20,
    "status": "overdue",
    "tags": ["gym", "friend"],
    "bio": "Workout partner from gym.",
    "goal": 10,
    "next_due_date": "2025-07-05"
  },
  {
    "id": 4,
    "name": "Ayesha Rahman",
    "picture": "https://res.cloudinary.com/dja4hd07v/image/upload/v1776302396/images_yblpy4.jpg",
    "email": "ayesha@example.com",
    "days_since_contact": 1,
    "status": "active",
    "tags": ["family"],
    "bio": "Cousin, very close connection.",
    "goal": 5,
    "next_due_date": "2025-07-25"
  },
  {
    "id": 5,
    "name": "David Smith",
    "picture": "https://res.cloudinary.com/dja4hd07v/image/upload/v1776313666/images_4_oseszz.jpg",
    "email": "david@example.com",
    "days_since_contact": 30,
    "status": "overdue",
    "tags": ["business"],
    "bio": "Client from previous project.",
    "goal": 15,
    "next_due_date": "2025-06-30"
  },
  {
    "id": 6,
    "name": "Nusrat Jahan",
    "picture": "https://res.cloudinary.com/dja4hd07v/image/upload/v1776301768/download_e5x4gp.jpg",
    "email": "nusrat@example.com",
    "days_since_contact": 6,
    "status": "pending",
    "tags": ["university"],
    "bio": "Classmate from university.",
    "goal": 10,
    "next_due_date": "2025-07-18"
  },
  {
    "id": 7,
    "name": "Alex Turner",
    "picture": "https://res.cloudinary.com/dja4hd07v/image/upload/v1776313665/images_6_oxxk0p.jpg",
    "email": "alex@example.com",
    "days_since_contact": 14,
    "status": "overdue",
    "tags": ["music", "friend"],
    "bio": "Met at a music festival.",
    "goal": 12,
    "next_due_date": "2025-07-01"
  },
  {
    "id": 8,
    "name": "Fatima Noor",
    "picture": "https://res.cloudinary.com/dja4hd07v/image/upload/v1776313388/images_1_wuvagv.jpg",
    "email": "fatima@example.com",
    "days_since_contact": 2,
    "status": "active",
    "tags": ["neighbor"],
    "bio": "Lives nearby, frequent chats.",
    "goal": 5,
    "next_due_date": "2025-07-22"
  },
  {
    "id": 9,
    "name": "James Wilson",
    "picture": "https://res.cloudinary.com/dja4hd07v/image/upload/v1776313665/images_7_n4y3dr.jpg",
    "email": "james@example.com",
    "days_since_contact": 18,
    "status": "overdue",
    "tags": ["work", "manager"],
    "bio": "Former manager at office.",
    "goal": 14,
    "next_due_date": "2025-07-03"
  },
  {
    "id": 10,
    "name": "Rafi Ahmed",
    "picture": "https://res.cloudinary.com/dja4hd07v/image/upload/v1776313665/download_2_u1irab.jpg",
    "email": "rafi@example.com",
    "days_since_contact": 4,
    "status": "pending",
    "tags": ["startup"],
    "bio": "Co-founder of a startup idea.",
    "goal": 8,
    "next_due_date": "2025-07-19"
  },
  {
    "id": 11,
    "name": "Emily Clark",
    "picture": "https://res.cloudinary.com/dja4hd07v/image/upload/v1776313403/download_1_b22fkg.jpg",
    "email": "emily@example.com",
    "days_since_contact": 9,
    "status": "active",
    "tags": ["travel"],
    "bio": "Met during a trip abroad.",
    "goal": 10,
    "next_due_date": "2025-07-15"
  },
  {
    "id": 12,
    "name": "Tanvir Hasan",
    "picture": "https://res.cloudinary.com/dja4hd07v/image/upload/v1776313664/download_3_ktggqs.jpg",
    "email": "tanvir@example.com",
    "days_since_contact": 25,
    "status": "overdue",
    "tags": ["school", "old friend"],
    "bio": "School friend, lost touch recently.",
    "goal": 20,
    "next_due_date": "2025-06-28"
  }
]